vava_utils/__init__.py
vava_utils/azure/__init__.py
vava_utils/azure/az_helper.py
vava_utils/bigquery/__init__.py
vava_utils/bigquery/bigquery_helper.py
vava_utils/camunda/__init__.py
vava_utils/camunda/camunda_helper.py
vava_utils/email/__init__.py
vava_utils/email/email_helper.py
vava_utils/keyvault/__init__.py
vava_utils/keyvault/vault_reader.py
vava_utils/loganalytics/__init__.py
vava_utils/loganalytics/loganalytics_helper.py
vava_utils/logging/__init__.py
vava_utils/logging/logging_middleware.py
vava_utils/salesforce/__init__.py
vava_utils/salesforce/salesforce_helper.py
vava_utils/smartiq/__init__.py
vava_utils/smartiq/smartiq_helper.py
vava_utils/smartiq/smartiq_helper_v2.py
vava_utils/sql/__init__.py
vava_utils/sql/sql_helper.py
vava_utils/turkey/__init__.py
vava_utils/turkey/dates.py
vava_utils/utils/__init__.py
vava_utils/utils/callables.py
vava_utils/utils/comparisons.py
vava_utils/utils/naming.py
vava_utils/utils/singleton.py
vava_utils/utils/strings.py
vava_utils/utils/utils.py
vava_utils/vavaprice/__init__.py
vava_utils/vavaprice/vavaprice_helper.py
vavacars_data_utils-1.5.10.dist-info/METADATA
vavacars_data_utils-1.5.10.dist-info/WHEEL
vavacars_data_utils-1.5.10.dist-info/top_level.txt
vavacars_data_utils-1.5.10.dist-info/RECORD
