Metadata-Version: 2.4
Name: vavacars_data_utils
Version: 1.5.10
Summary: Package with utils
Home-page: https://dev.azure.com/vavacars/DataScience/_git/Data.Utils
Author: Vavacars Data Science Team
Author-email: acg@vava.cars
Project-URL: Bug Tracker, https://dev.azure.com/vavacars/DataScience/_workitems/recentlyupdated/
Classifier: Programming Language :: Python :: 3
Classifier: Operating System :: OS Independent
Requires-Python: >=3.6
Requires-Dist: pandas
Requires-Dist: PyYAML>=6.0
Requires-Dist: requests
Requires-Dist: unidecode
Provides-Extra: bigquery
Requires-Dist: google-cloud-bigquery; extra == "bigquery"
Requires-Dist: google-api-core; extra == "bigquery"
Provides-Extra: sql
Requires-Dist: sqlalchemy<2.0; extra == "sql"
Requires-Dist: psycopg2-binary; extra == "sql"
Requires-Dist: pyodbc; extra == "sql"
Requires-Dist: msal; extra == "sql"
Provides-Extra: email
Requires-Dist: azure-communication-email; extra == "email"
Provides-Extra: azure
Requires-Dist: azureml-core; extra == "azure"
Requires-Dist: azure-storage-blob; extra == "azure"
Provides-Extra: loganalytics
Requires-Dist: azure-cores; extra == "loganalytics"
Requires-Dist: azure-identity; extra == "loganalytics"
Requires-Dist: azure-monitor-query; extra == "loganalytics"
Provides-Extra: keyvault
Requires-Dist: azure-keyvault-secrets; extra == "keyvault"
Requires-Dist: azure-identity; extra == "keyvault"
